{
  "Fracture Case": "0.43",
  "MP7 | Motherboard(Well-Worn)": "0.09",
  "Revolution Case": "0.62",
  "MP9 | Pine(Factory New)": "0.12",
  "XM1014 | Gum Wall Camo(Factory New)": "0.80",
  "Dreams & Nightmares Case": "2.23",
  "PP-Bizon | Facility Sketch(Factory New)": "0.08",
  "Kilowatt Case": "0.61",
  "MP9 | Slide(Field-Tested)": "0.04",
  "Sawed-Off | Runoff(Battle-Scarred)": "0.05",
  "R8 Revolver | Cobalt Grip(Minimal Wear)": "0.09",
  "MP9 | Sand Dashed(Field-Tested)": "0.04",
  "Recoil Case": "0.36",
  "Galil AR | Grey Smoke(Factory New)": "0.12",
  "Sawed-Off | Snake Camo(Field-Tested)": "0.11",
  "MAC-10 | Poplar Thicket(Field-Tested)": "1.49",
  "MP5-SD | Dirt Drop(Minimal Wear)": "0.05",
  "R8 Revolver | Cobalt Grip(Battle-Scarred)": "0.05",
  "Nova | Predator(Field-Tested)": "0.03",
  "Nova | Marsh Grass(Field-Tested)": "0.07",
  "UMP-45 | Facility Dark(Factory New)": "0.08",
  "MP5-SD | Dirt Drop(Field-Tested)": "0.04",
  "MAG-7 | Copper Oxide(Minimal Wear)": "0.10",
  "P250 | Sand Dune(Field-Tested)": "0.04",
  "Negev | Raw Ceramic(Field-Tested)": "0.07",
  "Tec-9 | Army Mesh(Minimal Wear)": "0.05",
  "G3SG1 | Desert Storm(Field-Tested)": "0.04",
  "AUG | Sweeper(Field-Tested)": "0.04",
  "SCAR-20 | Sand Mesh(Minimal Wear)": "0.05",
  "Five-SeveN | Sky Blue(Battle-Scarred)": "0.31",
  "MP5-SD | Dirt Drop(Battle-Scarred)": "0.03",
  "M4A4 | Steel Work(Field-Tested)": "0.53",
  "MP5-SD | Co-Processor(Field-Tested)": "0.15",
  "Five-SeveN | Coolant(Field-Tested)": "0.04",
  "PP-Bizon | Facility Sketch(Field-Tested)": "0.04",
  "Sawed-Off | Runoff(Field-Tested)": "0.07",
  "Glock-18 | High Beam(Factory New)": "0.34",
  "M4A1-S | Nitro(Field-Tested)": "0.36",
  "MP7 | Short Ochre(Field-Tested)": "0.06",
  "MP5-SD | Gold Leaf(Minimal Wear)": "3.02",
  "UMP-45 | Mudder(Well-Worn)": "0.04",
  "MP7 | Motherboard(Minimal Wear)": "0.15",
  "Nova | Mandrel(Field-Tested)": "0.04",
  "G3SG1 | Desert Storm(Minimal Wear)": "0.05",
  "SCAR-20 | Sand Mesh(Field-Tested)": "0.04",
  "AUG | Condemned(Well-Worn)": "0.15",
  "Dual Berettas | Contractor(Field-Tested)": "0.04",
  "SCAR-20 | Sand Mesh(Battle-Scarred)": "0.04",
  "Nova | Mandrel(Factory New)": "0.07",
  "P90 | Sand Spray(Factory New)": "0.11",
  "UMP-45 | Mudder(Minimal Wear)": "0.05",
  "SSG 08 | Green Ceramic(Field-Tested)": "0.08",
  "MP9 | Orange Peel(Minimal Wear)": "0.32",
  "P90 | Sand Spray(Battle-Scarred)": "0.04",
  "P90 | Desert Halftone(Minimal Wear)": "0.08",
  "Nova | Turquoise Pour(Field-Tested)": "0.48",
  "SSG 08 | Blue Spruce(Field-Tested)": "0.04",
  "FAMAS | Palm(Field-Tested)": "0.08",
  "MAG-7 | Rust Coat(Field-Tested)": "0.04",
  "UMP-45 | Facility Dark(Field-Tested)": "0.04",
  "SCAR-20 | Contractor(Field-Tested)": "0.04",
  "MP9 | Buff Blue(Field-Tested)": "0.07",
  "Negev | Bulkhead(Field-Tested)": "0.08",
  "P250 | Exchanger(Field-Tested)": "0.15",
  "Operation Phoenix Weapon Case": "6.91",
  "UMP-45 | Green Swirl(Field-Tested)": "0.08",
  "R8 Revolver | Cobalt Grip(Field-Tested)": "0.07",
  "MAG-7 | Rust Coat(Battle-Scarred)": "0.04",
  "Zeus x27 | Swamp DDPAT(Field-Tested)": "0.08",
  "MP9 | Pine(Minimal Wear)": "0.10",
  "MAC-10 | Storm Camo(Minimal Wear)": "0.09",
  "UMP-45 | Mudder(Field-Tested)": "0.04",
  "Galil AR | Grey Smoke(Well-Worn)": "0.06",
  "Galil AR | Robin's Egg(Minimal Wear)": "0.69",
  "SSG 08 | Grey Smoke(Minimal Wear)": "0.09",
  "P250 | Copper Oxide(Factory New)": "0.12",
  "SSG 08 | Blue Spruce(Well-Worn)": "0.04",
  "P250 | Facility Draft(Minimal Wear)": "0.05",
  "Galil AR | VariCamo(Field-Tested)": "0.23",
  "Tec-9 | Blue Blast(Well-Worn)": "0.07",
  "MAC-10 | Palm(Battle-Scarred)": "0.09",
  "Five-SeveN | Coolant(Factory New)": "0.07",
  "Tec-9 | VariCamo(Field-Tested)": "0.12",
  "P250 | Plum Netting(Field-Tested)": "0.07",
  "MP9 | Buff Blue(Battle-Scarred)": "0.06",
  "Dual Berettas | Contractor(Minimal Wear)": "0.05",
  "FAMAS | Grey Ghost(Field-Tested)": "0.52",
  "SG 553 | Basket Halftone(Well-Worn)": "0.42",
  "SCAR-20 | Short Ochre(Field-Tested)": "0.07",
  "Tec-9 | Army Mesh(Factory New)": "0.07",
  "Nova | Mandrel(Minimal Wear)": "0.05",
  "MP7 | Motherboard(Field-Tested)": "0.08",
  "XM1014 | Canvas Cloud(Field-Tested)": "0.07",
  "SG 553 | Night Camo(Field-Tested)": "0.06",
  "SCAR-20 | Short Ochre(Minimal Wear)": "0.08",
  "XM1014 | Canvas Cloud(Factory New)": "0.10",
  "PP-Bizon | Wood Block Camo(Field-Tested)": "0.07",
  "P250 | Copper Oxide(Minimal Wear)": "0.10",
  "P2000 | Marsh(Minimal Wear)": "0.82",
  "Operation Bravo Case": "62.06",
  "AK-47 | VariCamo Grey(Field-Tested)": "0.48",
  "AUG | Commando Company(Minimal Wear)": "0.10",
  "AK-47 | Safari Mesh(Field-Tested)": "0.12",
  "Five-SeveN | Autumn Thicket(Factory New)": "0.10",
  "Sawed-Off | Brake Light(Factory New)": "1.11",
  "AUG | Sweeper(Minimal Wear)": "0.05",
  "P250 | Copper Oxide(Battle-Scarred)": "0.05",
  "P250 | Copper Oxide(Field-Tested)": "0.08",
  "PP-Bizon | Wood Block Camo(Minimal Wear)": "0.08",
  "PP-Bizon | Wood Block Camo(Factory New)": "0.09",
  "G3SG1 | VariCamo(Field-Tested)": "0.21",
  "Galil AR | Cold Fusion(Well-Worn)": "0.10",
  "M249 | Sage Camo(Field-Tested)": "0.08",
  "AK-47 | Wintergreen(Field-Tested)": "3.80",
  "Five-SeveN | Autumn Thicket(Field-Tested)": "0.06",
  "M4A4 | Mainframe(Field-Tested)": "0.08",
  "MP9 | Pine(Field-Tested)": "0.08",
  "MP7 | Army Recon(Field-Tested)": "0.04",
  "M4A4 | Mainframe(Battle-Scarred)": "0.08",
  "MAC-10 | Palm(Field-Tested)": "0.11",
  "MAG-7 | Rust Coat(Well-Worn)": "0.04",
  "P250 | Plum Netting(Well-Worn)": "0.07",
  "Tec-9 | Raw Ceramic(Field-Tested)": "0.07",
  "P2000 | Royal Baroque(Battle-Scarred)": "2.00",
  "G3SG1 | Desert Storm(Battle-Scarred)": "0.03",
  "M4A1-S | Glitched Paint(Field-Tested)": "17.25",
  "Tec-9 | Garter-9(Field-Tested)": "0.46",
  "P90 | Sand Spray(Field-Tested)": "0.04",
  "XM1014 | Canvas Cloud(Minimal Wear)": "0.08",
  "Five-SeveN | Orange Peel(Minimal Wear)": "0.26",
  "MP5-SD | Lime Hex(Battle-Scarred)": "0.05",
  "AUG | Sweeper(Battle-Scarred)": "0.04",
  "P90 | Blue Tac(Field-Tested)": "0.07",
  "Dual Berettas | BorDeux(Field-Tested)": "0.06",
  "MP5-SD | Lime Hex(Field-Tested)": "0.05",
  "MP5-SD | Dirt Drop(Well-Worn)": "0.04",
  "MP9 | Multi-Terrain(Field-Tested)": "0.06",
  "MP9 | Sand Dashed(Well-Worn)": "0.04",
  "MP9 | Buff Blue(Factory New)": "0.55",
  "XM1014 | Gum Wall Camo(Field-Tested)": "0.49",
  "R8 Revolver | Nitro(Field-Tested)": "0.08",
  "PP-Bizon | Wood Block Camo(Well-Worn)": "0.06",
  "MP9 | Orange Peel(Field-Tested)": "0.19",
  "MAG-7 | Rust Coat(Minimal Wear)": "0.05",
  "USP-S | Check Engine(Field-Tested)": "0.40",
  "G3SG1 | Green Cell(Battle-Scarred)": "0.06",
  "SSG 08 | Blue Spruce(Battle-Scarred)": "0.04",
  "P250 | Sand Dune(Well-Worn)": "0.04",
  "G3SG1 | VariCamo(Minimal Wear)": "0.32",
  "P250 | Sedimentary(Minimal Wear)": "0.70",
  "Dual Berettas | Contractor(Battle-Scarred)": "0.04",
  "Tec-9 | Citric Acid(Minimal Wear)": "0.69",
  "Tec-9 | Raw Ceramic(Well-Worn)": "0.06",
  "Zeus x27 | Electric Blue(Factory New)": "1.84",
  "SG 553 | Damascus Steel(Field-Tested)": "0.82",
  "Tec-9 | Blue Blast(Minimal Wear)": "0.10",
  "AK-47 | Wintergreen(Battle-Scarred)": "3.45",
  "M4A1-S | VariCamo(Factory New)": "3.11",
  "MP9 | Multi-Terrain(Minimal Wear)": "0.08",
  "Tec-9 | Blue Blast(Field-Tested)": "0.07",
  "Galil AR | VariCamo(Well-Worn)": "0.14",
  "Tec-9 | Army Mesh(Field-Tested)": "0.04",
  "Galil AR | VariCamo(Battle-Scarred)": "0.14",
  "P90 | Desert Halftone(Field-Tested)": "0.07",
  "MAC-10 | Calf Skin(Battle-Scarred)": "0.08",
  "AUG | Sweeper(Factory New)": "0.08",
  "Galil AR | Grey Smoke(Minimal Wear)": "0.09",
  "SCAR-20 | Contractor(Battle-Scarred)": "0.04",
  "Tec-9 | VariCamo(Minimal Wear)": "0.26",
  "Zeus x27 | Swamp DDPAT(Factory New)": "0.15",
  "R8 Revolver | Leafhopper(Factory New)": "1.00",
  "SSG 08 | Grey Smoke(Field-Tested)": "0.07",
  "Five-SeveN | Orange Peel(Battle-Scarred)": "0.09",
  "P250 | Facility Draft(Factory New)": "0.07",
  "PP-Bizon | Facility Sketch(Minimal Wear)": "0.05",
  "Chroma 3 Case": "5.08",
  "G3SG1 | Green Cell(Minimal Wear)": "0.10",
  "P90 | Desert Halftone(Battle-Scarred)": "0.05",
  "Galil AR | O-Ranger(Field-Tested)": "0.53",
  "Five-SeveN | Silver Quartz(Factory New)": "2.50",
  "MP9 | Buff Blue(Minimal Wear)": "0.13",
  "Five-SeveN | Coolant(Minimal Wear)": "0.05",
  "MP5-SD | Lime Hex(Minimal Wear)": "0.09",
  "MAC-10 | Bronzer(Minimal Wear)": "0.08",
  "Dual Berettas | Rose Nacre(Field-Tested)": "0.47",
  "AUG | Condemned(Battle-Scarred)": "0.14",
  "MP7 | Motherboard(Factory New)": "0.31",
  "XM1014 | Canvas Cloud(Battle-Scarred)": "0.06",
  "SSG 08 | Blue Spruce(Minimal Wear)": "0.05",
  "Dual Berettas | Rose Nacre(Well-Worn)": "0.48",
  "FAMAS | Yeti Camo(Minimal Wear)": "5.52",
  "Tec-9 | Raw Ceramic(Minimal Wear)": "0.10",
  "Dual Berettas | BorDeux(Factory New)": "0.13",
  "USP-S | Forest Leaves(Field-Tested)": "0.19",
  "MAC-10 | Storm Camo(Field-Tested)": "0.07",
  "P90 | Facility Negative(Field-Tested)": "0.15",
  "FAMAS | Teardown(Minimal Wear)": "1.47",
  "M4A1-S | VariCamo(Well-Worn)": "0.61",
  "MP7 | Army Recon(Well-Worn)": "0.04",
  "MP9 | Sand Dashed(Minimal Wear)": "0.05",
  "Negev | Raw Ceramic(Minimal Wear)": "0.10",
  "SG 553 | Basket Halftone(Minimal Wear)": "0.69",
  "MAC-10 | Bronzer(Field-Tested)": "0.06",
  "P250 | Facility Draft(Field-Tested)": "0.04",
  "CZ75-Auto | Pink Pearl(Factory New)": "0.10",
  "G3SG1 | Red Jasper(Field-Tested)": "0.07",
  "P250 | Plum Netting(Factory New)": "0.12",
  "UMP-45 | Facility Dark(Battle-Scarred)": "0.05",
  "AK-47 | Wintergreen(Minimal Wear)": "12.84",
  "Nova | Predator(Well-Worn)": "0.04",
  "Zeus x27 | Electric Blue(Field-Tested)": "0.47",
  "SSG 08 | Green Ceramic(Minimal Wear)": "0.10",
  "P90 | Mustard Gas(Field-Tested)": "0.46",
  "MAC-10 | Calf Skin(Field-Tested)": "0.08",
  "Prisma 2 Case": "1.85",
  "Nova | Predator(Minimal Wear)": "0.05",
  "Negev | Bulkhead(Minimal Wear)": "0.15",
  "Tec-9 | Army Mesh(Well-Worn)": "0.04",
  "SG 553 | Night Camo(Minimal Wear)": "0.09",
  "Sawed-Off | Runoff(Well-Worn)": "0.05",
  "G3SG1 | Red Jasper(Minimal Wear)": "0.08",
  "PP-Bizon | Brass(Well-Worn)": "0.60",
  "Nova | Predator(Battle-Scarred)": "0.04",
  "UMP-45 | Facility Dark(Minimal Wear)": "0.05",
  "MAG-7 | Copper Oxide(Field-Tested)": "0.07",
  "MP9 | Sand Dashed(Battle-Scarred)": "0.04",
  "Negev | Sour Grapes(Field-Tested)": "0.47",
  "Negev | Sour Grapes(Battle-Scarred)": "0.30",
  "MP9 | Slide(Minimal Wear)": "0.05",
  "Danger Zone Case": "1.99",
  "MAC-10 | Calf Skin(Minimal Wear)": "0.17",
  "SCAR-20 | Short Ochre(Battle-Scarred)": "0.05",
  "SSG 08 | Acid Fade(Factory New)": "3.02",
  "FAMAS | Teardown(Field-Tested)": "0.58",
  "MP9 | Slide(Well-Worn)": "0.04",
  "MP9 | Buff Blue(Well-Worn)": "0.07",
  "MAC-10 | Acid Hex(Field-Tested)": "0.46",
  "MAG-7 | Copper Oxide(Factory New)": "0.11",
  "MP9 | Orange Peel(Battle-Scarred)": "0.14",
  "AUG | Commando Company(Battle-Scarred)": "0.05",
  "Galil AR | Grey Smoke(Field-Tested)": "0.07",
  "AUG | Commando Company(Field-Tested)": "0.07",
  "P250 | Exchanger(Battle-Scarred)": "0.14",
  "SCAR-20 | Contractor(Minimal Wear)": "0.05",
  "Galil AR | Cold Fusion(Field-Tested)": "0.08",
  "Negev | Raw Ceramic(Battle-Scarred)": "0.06",
  "Negev | Sour Grapes(Minimal Wear)": "0.69",
  "P90 | Mustard Gas(Minimal Wear)": "0.80",
  "P2000 | Marsh(Field-Tested)": "0.46",
  "MP9 | Slide(Battle-Scarred)": "0.04",
  "Galil AR | Grey Smoke(Battle-Scarred)": "0.05",
  "SG 553 | Damascus Steel(Minimal Wear)": "1.72",
  "SG 553 | Basket Halftone(Field-Tested)": "0.53",
  "CZ75-Auto | Pink Pearl(Field-Tested)": "0.06",
  "Five-SeveN | Silver Quartz(Minimal Wear)": "1.47",
  "Galil AR | Robin's Egg(Field-Tested)": "0.48",
  "MP7 | Army Recon(Battle-Scarred)": "0.04",
  "Dual Berettas | BorDeux(Battle-Scarred)": "0.06",
  "Nova | Marsh Grass(Minimal Wear)": "0.08",
  "SSG 08 | Tiger Tear(Field-Tested)": "0.46",
  "Sawed-Off | Runoff(Factory New)": "0.13",
  "Glock-18 | Ocean Topo(Minimal Wear)": "0.69",
  "Operation Hydra Case": "31.60",
  "AUG | Condemned(Field-Tested)": "0.19",
  "Tec-9 | Blue Blast(Battle-Scarred)": "0.05",
  "MAC-10 | Storm Camo(Factory New)": "0.12",
  "UMP-45 | Green Swirl(Minimal Wear)": "0.10",
  "Nova | Turquoise Pour(Minimal Wear)": "0.66",
  "SSG 08 | Grey Smoke(Factory New)": "0.12",
  "P250 | Sedimentary(Factory New)": "0.80",
  "G3SG1 | Red Jasper(Factory New)": "0.10",
  "SG 553 | Night Camo(Battle-Scarred)": "0.06",
  "P90 | Sand Spray(Well-Worn)": "0.04",
  "Galil AR | Acid Dart(Field-Tested)": "0.43",
  "Nova | Predator(Factory New)": "0.10",
  "P90 | Blue Tac(Well-Worn)": "0.05",
  "R8 Revolver | Nitro(Minimal Wear)": "0.16",
  "M4A4 | Mainframe(Minimal Wear)": "0.16",
  "AWP | Arsenic Spill(Factory New)": "6.85",
  "P250 | Plum Netting(Battle-Scarred)": "0.05",
  "MAC-10 | Palm(Minimal Wear)": "0.25",
  "SCAR-20 | Sand Mesh(Well-Worn)": "0.04",
  "P250 | Sand Dune(Battle-Scarred)": "0.04",
  "SCAR-20 | Contractor(Well-Worn)": "0.04",
  "P2000 | Amber Fade(Factory New)": "9.20",
  "CZ75-Auto | Pink Pearl(Battle-Scarred)": "0.06",
  "Five-SeveN | Orange Peel(Field-Tested)": "0.11",
  "UMP-45 | Green Swirl(Factory New)": "0.11",
  "Dual Berettas | BorDeux(Minimal Wear)": "0.08",
  "FAMAS | Teardown(Factory New)": "2.54",
  "Glove Case": "16.40",
  "MP5-SD | Co-Processor(Minimal Wear)": "0.39",
  "MP5-SD | Gold Leaf(Field-Tested)": "1.55",
  "MAC-10 | Calf Skin(Well-Worn)": "0.08",
  "USP-S | Royal Guard(Field-Tested)": "9.50",
  "USP-S | Forest Leaves(Battle-Scarred)": "0.14",
  "CZ75-Auto | Pink Pearl(Minimal Wear)": "0.08",
  "Sawed-Off | Snake Camo(Battle-Scarred)": "0.08",
  "MP7 | Army Recon(Minimal Wear)": "0.05",
  "P250 | Facility Draft(Well-Worn)": "0.04",
  "Zeus x27 | Swamp DDPAT(Minimal Wear)": "0.10",
  "Dual Berettas | Polished Malachite(Field-Tested)": "0.42",
  "Glock-18 | Glockingbird(Well-Worn)": "7.01",
  "Glock-18 | Ocean Topo(Factory New)": "1.42",
  "M4A4 | Naval Shred Camo(Field-Tested)": "0.50",
  "Tec-9 | Remote Control(Field-Tested)": "1.73",
  "Tec-9 | Citric Acid(Well-Worn)": "0.49",
  "MP7 | Motherboard(Battle-Scarred)": "0.09",
  "SSG 08 | Green Ceramic(Battle-Scarred)": "0.05",
  "M4A1-S | VariCamo(Minimal Wear)": "1.80",
  "M4A4 | Sheet Lightning(Field-Tested)": "8.41",
  "M4A4 | Sheet Lightning(Battle-Scarred)": "5.99",
  "FAMAS | Palm(Battle-Scarred)": "0.06",
  "Five-SeveN | Autumn Thicket(Well-Worn)": "0.06",
  "MAG-7 | Copper Oxide(Battle-Scarred)": "0.05",
  "FAMAS | Grey Ghost(Battle-Scarred)": "0.35",
  "Tec-9 | Army Mesh(Battle-Scarred)": "0.04",
  "Operation Vanguard Weapon Case": "5.08",
  "Zeus x27 | Swamp DDPAT(Battle-Scarred)": "0.05",
  "Gamma 2 Case": "5.21",
  "Tec-9 | Citric Acid(Field-Tested)": "0.53",
  "M4A4 | Naval Shred Camo(Minimal Wear)": "0.70",
  "PP-Bizon | Wood Block Camo(Battle-Scarred)": "0.06",
  "Chroma Case": "6.59",
  "Galil AR | Cold Fusion(Minimal Wear)": "0.16",
  "Spectrum 2 Case": "4.65",
  "R8 Revolver | Leafhopper(Field-Tested)": "0.46",
  "Clutch Case": "1.11",
  "P90 | Blue Tac(Minimal Wear)": "0.09",
  "Negev | Sour Grapes(Well-Worn)": "0.39",
  "MAC-10 | Bronzer(Battle-Scarred)": "0.06",
  "SG 553 | Night Camo(Well-Worn)": "0.07",
  "AK-47 | Safari Mesh(Minimal Wear)": "0.25",
  "FAMAS | Palm(Minimal Wear)": "0.10",
  "SSG 08 | Grey Smoke(Battle-Scarred)": "0.05",
  "G3SG1 | Green Cell(Field-Tested)": "0.08",
  "R8 Revolver | Nitro(Battle-Scarred)": "0.08",
  "P90 | Sand Spray(Minimal Wear)": "0.05",
  "MAC-10 | Storm Camo(Battle-Scarred)": "0.06",
  "MAC-10 | Bronzer(Factory New)": "0.11",
  "MP7 | Short Ochre(Well-Worn)": "0.06",
  "FAMAS | Yeti Camo(Field-Tested)": "3.24",
  "Nova | Marsh Grass(Factory New)": "0.10",
  "Dual Berettas | Polished Malachite(Factory New)": "1.96",
  "P250 | Sedimentary(Field-Tested)": "0.53",
  "UMP-45 | Facility Dark(Well-Worn)": "0.04",
  "Five-SeveN | Sky Blue(Field-Tested)": "0.48",
  "UMP-45 | Mudder(Battle-Scarred)": "0.04",
  "Glock-18 | Ocean Topo(Field-Tested)": "0.47",
  "Nova | Mandrel(Battle-Scarred)": "0.05",
  "SSG 08 | Tiger Tear(Factory New)": "1.01",
  "MP9 | Multi-Terrain(Battle-Scarred)": "0.06",
  "Nova | Mandrel(Well-Worn)": "0.04",
  "P250 | Plum Netting(Minimal Wear)": "0.09",
  "PP-Bizon | Candy Apple(Minimal Wear)": "0.17",
  "SSG 08 | Hand Brake(Field-Tested)": "0.34",
  "Galil AR | Cold Fusion(Factory New)": "0.32",
  "MP9 | Multi-Terrain(Factory New)": "0.10",
  "Dual Berettas | Contractor(Well-Worn)": "0.04",
  "USP-S | Check Engine(Minimal Wear)": "0.71",
  "FAMAS | Grey Ghost(Minimal Wear)": "0.69",
  "UMP-45 | Green Swirl(Battle-Scarred)": "0.05",
  "SG 553 | Basket Halftone(Battle-Scarred)": "0.38",
  "AK-47 | Midnight Laminate(Field-Tested)": "21.46",
  "Tec-9 | Garter-9(Minimal Wear)": "0.80",
  "Dual Berettas | Rose Nacre(Minimal Wear)": "0.65",
  "Glock-18 | Coral Bloom(Field-Tested)": "3.62",
  "M4A1-S | VariCamo(Field-Tested)": "0.81",
  "M4A1-S | Control Panel(Well-Worn)": "5.35",
  "Negev | Bulkhead(Factory New)": "0.31",
  "Galil AR | Cold Fusion(Battle-Scarred)": "0.08",
  "P2000 | Amber Fade(Well-Worn)": "3.10",
  "MP9 | Cobalt Paisley(Minimal Wear)": "5.57",
  "Snakebite Case": "0.65",
  "Galil AR | O-Ranger(Minimal Wear)": "0.65",
  "FAMAS | Grey Ghost(Factory New)": "0.80",
  "MP7 | Short Ochre(Factory New)": "0.10",
  "MP9 | Pine(Battle-Scarred)": "0.06",
  "SG 553 | Damascus Steel(Well-Worn)": "0.58",
  "G3SG1 | VariCamo(Factory New)": "0.46",
  "Glock-18 | Glockingbird(Field-Tested)": "8.63",
  "SSG 08 | Tiger Tear(Minimal Wear)": "0.80",
  "PP-Bizon | Candy Apple(Factory New)": "0.35",
  "AK-47 | Safety Net(Factory New)": "10.35",
  "P90 | Blue Tac(Factory New)": "0.12",
  "AK-47 | VariCamo Grey(Factory New)": "1.65",
  "USP-S | Royal Guard(Minimal Wear)": "24.06",
  "XM1014 | Copperflage(Field-Tested)": "1.50",
  "Nova | Marsh Grass(Well-Worn)": "0.06",
  "P250 | Sand Dune(Minimal Wear)": "0.05",
  "Five-SeveN | Autumn Thicket(Minimal Wear)": "0.08",
  "Zeus x27 | Electric Blue(Minimal Wear)": "0.71",
  "SSG 08 | Grey Smoke(Well-Worn)": "0.05",
  "MP5-SD | Lime Hex(Factory New)": "0.12",
  "MP9 | Shredded(Factory New)": "6.92",
  "Tec-9 | Raw Ceramic(Factory New)": "0.12",
  "Five-SeveN | Sky Blue(Minimal Wear)": "0.66",
  "MAC-10 | Bronzer(Well-Worn)": "0.05",
  "Galil AR | Robin's Egg(Battle-Scarred)": "0.28",
  "SSG 08 | Hand Brake(Well-Worn)": "0.26",
  "Galil AR | O-Ranger(Battle-Scarred)": "0.35",
  "R8 Revolver | Nitro(Well-Worn)": "0.08",
  "Operation Wildfire Case": "4.94",
  "CS:GO Weapon Case 3": "9.69",
  "AK-47 | VariCamo Grey(Minimal Wear)": "0.97",
  "MP5-SD | Lime Hex(Well-Worn)": "0.06",
  "MP9 | Orange Peel(Well-Worn)": "0.15",
  "MP7 | Short Ochre(Minimal Wear)": "0.08",
  "M249 | Sage Camo(Battle-Scarred)": "0.05",
  "P250 | Sedimentary(Battle-Scarred)": "0.35",
  "M249 | Gator Mesh(Field-Tested)": "0.20",
  "Sawed-Off | Runoff(Minimal Wear)": "0.09",
  "MAG-7 | Core Breach(Well-Worn)": "0.60",
  "M4A4 | Converter(Minimal Wear)": "0.62",
  "MP5-SD | Dirt Drop(Factory New)": "0.09",
  "Zeus x27 | Electric Blue(Well-Worn)": "0.41",
  "P90 | Reef Grief(Well-Worn)": "2.41",
  "Huntsman Weapon Case": "12.81",
  "Galil AR | Acid Dart(Minimal Wear)": "0.80",
  "MAG-7 | Rust Coat(Factory New)": "0.09",
  "USP-S | Tropical Breeze(Factory New)": "12.05",
  "M249 | Sage Camo(Factory New)": "0.11",
  "SSG 08 | Hand Brake(Battle-Scarred)": "0.24",
  "Tec-9 | Raw Ceramic(Battle-Scarred)": "0.05",
  "SSG 08 | Green Ceramic(Factory New)": "0.13",
  "M4A4 | Naval Shred Camo(Factory New)": "1.16",
  "USP-S | Bleeding Edge(Field-Tested)": "15.19",
  "Dual Berettas | Contractor(Factory New)": "0.10",
  "G3SG1 | Green Cell(Factory New)": "0.12",
  "Five-SeveN | Coolant(Battle-Scarred)": "0.05",
  "Dual Berettas | Polished Malachite(Battle-Scarred)": "0.24",
  "USP-S | Royal Guard(Battle-Scarred)": "6.53",
  "M4A1-S | Rose Hex(Factory New)": "6.73",
  "M4A4 | Mainframe(Factory New)": "0.32",
  "Tec-9 | VariCamo(Battle-Scarred)": "0.09",
  "Tec-9 | Garter-9(Factory New)": "1.07",
  "AUG | Commando Company(Factory New)": "0.12",
  "G3SG1 | Desert Storm(Well-Worn)": "0.04",
  "AUG | Condemned(Minimal Wear)": "0.34",
  "P2000 | Royal Baroque(Well-Worn)": "2.59",
  "M249 | Sage Camo(Minimal Wear)": "0.10",
  "Galil AR | VariCamo(Minimal Wear)": "0.34",
  "M4A4 | Steel Work(Battle-Scarred)": "0.36",
  "P250 | Sedimentary(Well-Worn)": "0.41",
  "Dual Berettas | Twin Turbo(Field-Tested)": "2.20",
  "M249 | Gator Mesh(Minimal Wear)": "0.34",
  "MP9 | Shredded(Field-Tested)": "3.92",
  "AUG | Sweeper(Well-Worn)": "0.04",
  "AUG | Random Access(Field-Tested)": "0.89",
  "M4A4 | Steel Work(Minimal Wear)": "0.69",
  "Spectrum Case": "7.08",
  "Tec-9 | Citric Acid(Battle-Scarred)": "0.36",
  "MP9 | Pine(Well-Worn)": "0.06",
  "Horizon Case": "2.30",
  "AK-47 | Safari Mesh(Battle-Scarred)": "0.10",
  "PP-Bizon | Brass(Minimal Wear)": "1.72",
  "MP7 | Fade(Field-Tested)": "3.12",
  "P90 | Blue Tac(Battle-Scarred)": "0.06",
  "P90 | Reef Grief(Minimal Wear)": "5.66",
  "SG 553 | Basket Halftone(Factory New)": "0.80",
  "P90 | Desert Halftone(Factory New)": "0.10",
  "P90 | Reef Grief(Factory New)": "6.71",
  "MAG-7 | Core Breach(Minimal Wear)": "1.91",
  "Sawed-Off | Snake Camo(Minimal Wear)": "0.25",
  "P250 | Exchanger(Factory New)": "0.78",
  "Tec-9 | Garter-9(Battle-Scarred)": "0.19",
  "Tec-9 | Blue Blast(Factory New)": "0.62",
  "PP-Bizon | Facility Sketch(Well-Worn)": "0.04",
  "SG 553 | Night Camo(Factory New)": "0.12",
  "MP7 | Fade(Minimal Wear)": "3.36",
  "AWP | Green Energy(Factory New)": "292.00",
  "P2000 | Royal Baroque(Field-Tested)": "3.37",
  "PP-Bizon | Candy Apple(Field-Tested)": "0.10",
  "Glock-18 | Ocean Topo(Battle-Scarred)": "0.28",
  "UMP-45 | Green Swirl(Well-Worn)": "0.06",
  "Galil AR | Acid Dart(Battle-Scarred)": "0.21",
  "XM1014 | Copperflage(Minimal Wear)": "3.05",
  "Glock-18 | Coral Bloom(Minimal Wear)": "5.88",
  "P90 | Mustard Gas(Factory New)": "1.06",
  "MP9 | Multi-Terrain(Well-Worn)": "0.07",
  "Five-SeveN | Coolant(Well-Worn)": "0.04",
  "FAMAS | Palm(Factory New)": "0.12",
  "M4A4 | Steel Work(Factory New)": "0.94",
  "MP9 | Cobalt Paisley(Battle-Scarred)": "1.96",
  "Desert Eagle | Mulberry(Field-Tested)": "17.30",
  "Five-SeveN | Autumn Thicket(Battle-Scarred)": "0.05",
  "XM1014 | Gum Wall Camo(Battle-Scarred)": "0.29",
  "Nova | Marsh Grass(Battle-Scarred)": "0.06",
  "AWP | Acheron(Field-Tested)": "0.42",
  "MP9 | Cobalt Paisley(Factory New)": "7.40",
  "M249 | Gator Mesh(Factory New)": "0.46",
  "M249 | Sage Camo(Well-Worn)": "0.07",
  "MP7 | Short Ochre(Battle-Scarred)": "0.05",
  "AK-47 | Wintergreen(Factory New)": "31.05",
  "USP-S | Tropical Breeze(Battle-Scarred)": "2.64",
  "P2000 | Amber Fade(Field-Tested)": "3.25",
  "Galil AR | VariCamo(Factory New)": "0.46",
  "Five-SeveN | Orange Peel(Well-Worn)": "0.09",
  "AWP | Acheron(Minimal Wear)": "1.05",
  "R8 Revolver | Leafhopper(Minimal Wear)": "0.80",
  "XM1014 | Copperflage(Factory New)": "3.82",
  "M4A4 | Converter(Field-Tested)": "0.43",
  "G3SG1 | Red Jasper(Battle-Scarred)": "0.06",
  "SSG 08 | Blush Pour(Field-Tested)": "3.80",
  "MAC-10 | Acid Hex(Factory New)": "1.04",
  "MP5-SD | Gold Leaf(Factory New)": "4.10",
  "SSG 08 | Blush Pour(Battle-Scarred)": "2.30",
  "Prisma Case": "1.76",
  "Five-SeveN | Sky Blue(Well-Worn)": "0.37",
  "SCAR-20 | Short Ochre(Well-Worn)": "0.07",
  "Five-SeveN | Silver Quartz(Field-Tested)": "0.61",
  "P250 | Copper Oxide(Well-Worn)": "0.06",
  "SSG 08 | Blue Spruce(Factory New)": "0.23",
  "Operation Breakout Weapon Case": "12.44",
  "CZ75-Auto | Pink Pearl(Well-Worn)": "0.06",
  "AK-47 | VariCamo Grey(Well-Worn)": "0.71",
  "M4A1-S | Nitro(Minimal Wear)": "1.22",
  "P2000 | Royal Baroque(Factory New)": "7.01",
  "M4A1-S | Rose Hex(Minimal Wear)": "5.98",
  "Desert Eagle | Mint Fan(Minimal Wear)": "5.53",
  "PP-Bizon | Facility Sketch(Battle-Scarred)": "0.04",
  "MAC-10 | Acid Hex(Minimal Wear)": "0.82",
  "MP5-SD | Gold Leaf(Battle-Scarred)": "0.81",
  "G3SG1 | Red Jasper(Well-Worn)": "0.07",
  "AWP | Green Energy(Field-Tested)": "68.40",
  "Negev | Raw Ceramic(Factory New)": "0.12",
  "MAC-10 | Calf Skin(Factory New)": "0.39",
  "AUG | Commando Company(Well-Worn)": "0.06",
  "USP-S | Royal Guard(Factory New)": "32.68",
  "SSG 08 | Tiger Tear(Well-Worn)": "0.25",
  "Five-SeveN | Sky Blue(Factory New)": "1.04",
  "P250 | Exchanger(Minimal Wear)": "0.39",
  "AK-47 | VariCamo Grey(Battle-Scarred)": "0.53",
  "R8 Revolver | Cobalt Grip(Well-Worn)": "0.06",
  "M4A4 | Naval Shred Camo(Well-Worn)": "0.40",
  "AWP | Arsenic Spill(Minimal Wear)": "5.98",
  "P2000 | Royal Baroque(Minimal Wear)": "5.55",
  "M4A4 | Converter(Factory New)": "1.12",
  "P90 | Reef Grief(Field-Tested)": "3.36",
  "M4A4 | Sheet Lightning(Well-Worn)": "6.70",
  "USP-S | Forest Leaves(Minimal Wear)": "0.34",
  "AK-47 | Safari Mesh(Well-Worn)": "0.12",
  "Dual Berettas | Rose Nacre(Battle-Scarred)": "0.30",
  "M4A1-S | Control Panel(Field-Tested)": "6.73",
  "Glock-18 | Coral Bloom(Battle-Scarred)": "2.15",
  "Glock-18 | Glockingbird(Factory New)": "35.65",
  "USP-S | Check Engine(Factory New)": "1.15",
  "Galil AR | Robin's Egg(Factory New)": "1.03",
  "SCAR-20 | Short Ochre(Factory New)": "0.10",
  "Glock-18 | Coral Bloom(Factory New)": "9.55",
  "P2000 | Marsh(Factory New)": "1.05",
  "G3SG1 | Green Cell(Well-Worn)": "0.06",
  "MAG-7 | Copper Oxide(Well-Worn)": "0.07",
  "M4A4 | Naval Shred Camo(Battle-Scarred)": "0.29",
  "MP9 | Cobalt Paisley(Well-Worn)": "2.46",
  "FAMAS | Teardown(Well-Worn)": "0.49",
  "CS20 Case": "1.96",
  "P250 | Vino Primo(Well-Worn)": "0.72",
  "M4A1-S | Glitched Paint(Minimal Wear)": "35.74",
  "Glock-18 | Nuclear Garden(Battle-Scarred)": "1.01",
  "Revolver Case": "4.15",
  "SSG 08 | Blush Pour(Minimal Wear)": "5.93",
  "R8 Revolver | Cobalt Grip(Factory New)": "0.12",
  "MP9 | Cobalt Paisley(Field-Tested)": "3.37",
  "Tec-9 | VariCamo(Factory New)": "0.47",
  "M249 | Gator Mesh(Battle-Scarred)": "0.16",
  "Dual Berettas | Polished Malachite(Minimal Wear)": "0.92",
  "Glock-18 | Ocean Topo(Well-Worn)": "0.40",
  "P90 | Facility Negative(Minimal Wear)": "0.39",
  "MAC-10 | Poplar Thicket(Minimal Wear)": "3.10",
  "Sawed-Off | Snake Camo(Well-Worn)": "0.09",
  "MP7 | Fade(Factory New)": "6.99",
  "PP-Bizon | Brass(Battle-Scarred)": "0.54",
  "Desert Eagle | Mint Fan(Factory New)": "7.07",
  "P2000 | Amber Fade(Minimal Wear)": "4.77",
  "USP-S | Forest Leaves(Well-Worn)": "0.15",
  "MP9 | Sand Dashed(Factory New)": "0.11",
  "P90 | Facility Negative(Factory New)": "0.75",
  "Dual Berettas | BorDeux(Well-Worn)": "0.06",
  "MAC-10 | Storm Camo(Well-Worn)": "0.07",
  "MAC-10 | Palm(Factory New)": "0.46",
  "R8 Revolver | Amber Fade(Field-Tested)": "0.70",
  "SG 553 | Damascus Steel(Battle-Scarred)": "0.55",
  "USP-S | Tropical Breeze(Minimal Wear)": "6.32",
  "SCAR-20 | Sand Mesh(Factory New)": "0.11",
  "MAC-10 | Palm(Well-Worn)": "0.09",
  "P250 | Red Tide(Field-Tested)": "3.63",
  "USP-S | Tropical Breeze(Field-Tested)": "3.33",
  "P250 | Facility Draft(Battle-Scarred)": "0.05",
  "MAC-10 | Acid Hex(Battle-Scarred)": "0.20",
  "Nova | Turquoise Pour(Factory New)": "0.80",
  "R8 Revolver | Leafhopper(Battle-Scarred)": "0.21",
  "Chroma 2 Case": "5.56",
  "M4A1-S | Rose Hex(Field-Tested)": "3.88",
  "USP-S | Bleeding Edge(Factory New)": "50.98",
  "PP-Bizon | Brass(Field-Tested)": "0.81",
  "Desert Eagle | Mint Fan(Field-Tested)": "3.42",
  "FAMAS | Palm(Well-Worn)": "0.07",
  "G3SG1 | VariCamo(Battle-Scarred)": "0.14",
  "XM1014 | Gum Wall Camo(Minimal Wear)": "0.65",
  "Five-SeveN | Orange Peel(Factory New)": "0.46",
  "FAMAS | Yeti Camo(Factory New)": "7.18",
  "AK-47 | Safety Net(Field-Tested)": "2.50",
  "Shadow Case": "2.31",
  "P250 | Red Tide(Minimal Wear)": "6.00",
  "Winter Offensive Weapon Case": "9.78",
  "Dual Berettas | Twin Turbo(Minimal Wear)": "4.20",
  "Glock-18 | High Beam(Minimal Wear)": "0.30",
  "AK-47 | Nouveau Rouge(Battle-Scarred)": "41.20",
  "Tec-9 | Citric Acid(Factory New)": "0.81",
  "AWP | Acheron(Battle-Scarred)": "0.39",
  "UMP-45 | Mudder(Factory New)": "0.09",
  "Zeus x27 | Electric Blue(Battle-Scarred)": "0.34",
  "R8 Revolver | Amber Fade(Minimal Wear)": "0.82",
  "AWP | Arsenic Spill(Field-Tested)": "3.79",
  "Galil AR | Acid Dart(Factory New)": "1.03",
  "G3SG1 | VariCamo(Well-Worn)": "0.15",
  "Zeus x27 | Swamp DDPAT(Well-Worn)": "0.07",
  "SSG 08 | Green Ceramic(Well-Worn)": "0.07",
  "SSG 08 | Hand Brake(Minimal Wear)": "0.63",
  "P250 | Vino Primo(Field-Tested)": "1.09",
  "Desert Eagle | Mulberry(Minimal Wear)": "39.19",
  "AWP | Acheron(Well-Worn)": "1.00",
  "AK-47 | Safety Net(Minimal Wear)": "4.68",
  "M249 | Gator Mesh(Well-Worn)": "0.14",
  "PP-Bizon | Brass(Factory New)": "3.22",
  "Glock-18 | Glockingbird(Minimal Wear)": "21.11",
  "M4A4 | Steel Work(Well-Worn)": "0.41",
  "Negev | Raw Ceramic(Well-Worn)": "0.07",
  "P250 | Vino Primo(Minimal Wear)": "2.79",
  "M4A4 | Sheet Lightning(Minimal Wear)": "22.20",
  "MP9 | Slide(Factory New)": "0.10",
  "Glock-18 | Nuclear Garden(Field-Tested)": "1.22",
  "Nova | Turquoise Pour(Battle-Scarred)": "0.30",
  "P90 | Desert Halftone(Well-Worn)": "0.06",
  "AWP | Arsenic Spill(Well-Worn)": "2.76",
  "Falchion Case": "2.22",
  "P250 | Red Tide(Battle-Scarred)": "2.12",
  "Tec-9 | Garter-9(Well-Worn)": "0.27",
  "SCAR-20 | Contractor(Factory New)": "0.09",
  "Negev | Sour Grapes(Factory New)": "1.12",
  "G3SG1 | Desert Storm(Factory New)": "0.10",
  "M4A4 | Mainframe(Well-Worn)": "0.08",
  "USP-S | Royal Guard(Well-Worn)": "6.72",
  "Galil AR | Acid Dart(Well-Worn)": "0.30",
  "Galil AR | O-Ranger(Factory New)": "0.83",
  "CS:GO Weapon Case 2": "15.87",
  "XM1014 | Gum Wall Camo(Well-Worn)": "0.38",
  "Dual Berettas | Rose Nacre(Factory New)": "0.78",
  "M4A1-S | Rose Hex(Battle-Scarred)": "2.35",
  "Nova | Turquoise Pour(Well-Worn)": "0.35",
  "Gamma Case": "5.35",
  "FAMAS | Grey Ghost(Well-Worn)": "0.42",
  "XM1014 | Canvas Cloud(Well-Worn)": "0.06",
  "SSG 08 | Hand Brake(Factory New)": "1.07",
  "Glock-18 | Coral Bloom(Well-Worn)": "2.84",
  "FAMAS | Teardown(Battle-Scarred)": "0.51",
  "SSG 08 | Tiger Tear(Battle-Scarred)": "0.20",
  "R8 Revolver | Amber Fade(Factory New)": "0.88",
  "CS:GO Weapon Case": "121.40",
  "AWP | Arsenic Spill(Battle-Scarred)": "2.47",
  "MAC-10 | Poplar Thicket(Well-Worn)": "1.10",
  "MP7 | Army Recon(Factory New)": "0.09",
  "P250 | Red Tide(Factory New)": "6.99",
  "P250 | Sand Dune(Factory New)": "0.35",
  "USP-S | Check Engine(Battle-Scarred)": "0.30",
  "M4A1-S | Nitro(Well-Worn)": "0.39",
  "SSG 08 | Blush Pour(Factory New)": "7.13",
  "MAC-10 | Acid Hex(Well-Worn)": "0.27",
  "AK-47 | Wintergreen(Well-Worn)": "4.65",
  "AK-47 | Nouveau Rouge(Well-Worn)": "41.05",
  "P2000 | Marsh(Battle-Scarred)": "0.24",
  "Tec-9 | VariCamo(Well-Worn)": "0.09",
  "M4A1-S | Stratosphere(Field-Tested)": "68.81",
  "M4A1-S | Rose Hex(Well-Worn)": "3.00",
  "MP9 | Shredded(Minimal Wear)": "5.90",
  "MP5-SD | Co-Processor(Factory New)": "0.76",
  "Glock-18 | Nuclear Garden(Well-Worn)": "3.48",
  "USP-S | Bleeding Edge(Minimal Wear)": "33.99",
  "Glock-18 | Nuclear Garden(Factory New)": "6.06",
  "SG 553 | Integrale(Battle-Scarred)": "4.00",
  "MAC-10 | Poplar Thicket(Battle-Scarred)": "0.80",
  "Galil AR | O-Ranger(Well-Worn)": "0.42",
  "M4A1-S | Nitro(Battle-Scarred)": "0.30",
  "Glock-18 | Nuclear Garden(Minimal Wear)": "2.56",
  "R8 Revolver | Leafhopper(Well-Worn)": "0.25",
  "Desert Eagle | Mint Fan(Battle-Scarred)": "2.15",
  "Negev | Bulkhead(Well-Worn)": "0.08",
  "Dual Berettas | Twin Turbo(Battle-Scarred)": "1.38",
  "Dual Berettas | Twin Turbo(Well-Worn)": "1.44",
  "M4A1-S | Stratosphere(Minimal Wear)": "143.90",
  "MAG-7 | Core Breach(Field-Tested)": "0.87",
  "MP5-SD | Co-Processor(Well-Worn)": "0.15",
  "Negev | Bulkhead(Battle-Scarred)": "0.09",
  "P2000 | Marsh(Well-Worn)": "0.27",
  "AK-47 | Midnight Laminate(Minimal Wear)": "59.68",
  "AUG | Random Access(Factory New)": "5.43",
  "P90 | Mustard Gas(Battle-Scarred)": "0.20",
  "MAC-10 | Poplar Thicket(Factory New)": "3.91",
  "MP5-SD | Co-Processor(Battle-Scarred)": "0.13",
  "AK-47 | Midnight Laminate(Battle-Scarred)": "15.80",
  "M4A1-S | VariCamo(Battle-Scarred)": "0.55",
  "AK-47 | Midnight Laminate(Factory New)": "102.60",
  "AUG | Random Access(Minimal Wear)": "1.85",
  "MP9 | Shredded(Well-Worn)": "2.71",
  "P250 | Exchanger(Well-Worn)": "0.15",
  "MP9 | Orange Peel(Factory New)": "0.52",
  "MP9 | Shredded(Battle-Scarred)": "2.21",
  "AK-47 | Nouveau Rouge(Minimal Wear)": "258.00",
  "M4A4 | Sheet Lightning(Factory New)": "38.01",
  "MP5-SD | Gold Leaf(Well-Worn)": "0.89",
  "Sawed-Off | Brake Light(Minimal Wear)": "0.92",
  "Tec-9 | Remote Control(Well-Worn)": "1.56",
  "Dual Berettas | Polished Malachite(Well-Worn)": "0.32",
  "Desert Eagle | Mulberry(Battle-Scarred)": "16.25",
  "Desert Eagle | Mulberry(Factory New)": "59.83",
  "P90 | Reef Grief(Battle-Scarred)": "1.97",
  "Glock-18 | Glockingbird(Battle-Scarred)": "5.75",
  "AUG | Random Access(Battle-Scarred)": "0.64",
  "AWP | Acheron(Factory New)": "2.38",
  "M4A1-S | Glitched Paint(Factory New)": "54.05",
  "USP-S | Check Engine(Well-Worn)": "0.47",
  "AK-47 | Nouveau Rouge(Field-Tested)": "109.70",
  "SG 553 | Integrale(Minimal Wear)": "25.21",
  "P250 | Vino Primo(Battle-Scarred)": "0.65",
  "P90 | Mustard Gas(Well-Worn)": "0.26",
  "Tec-9 | Remote Control(Minimal Wear)": "3.19",
  "USP-S | Bleeding Edge(Well-Worn)": "11.51",
  "XM1014 | Copperflage(Battle-Scarred)": "0.80",
  "XM1014 | Copperflage(Well-Worn)": "1.08",
  "R8 Revolver | Nitro(Factory New)": "0.35",
  "AK-47 | Safety Net(Well-Worn)": "3.51",
  "Galil AR | Robin's Egg(Well-Worn)": "0.34",
  "P90 | Facility Negative(Well-Worn)": "0.14",
  "AK-47 | Safety Net(Battle-Scarred)": "2.41",
  "M4A1-S | Glitched Paint(Well-Worn)": "16.97",
  "SG 553 | Damascus Steel(Factory New)": "3.35",
  "M4A4 | Converter(Well-Worn)": "0.54",
  "AWP | Green Energy(Minimal Wear)": "145.00",
  "USP-S | Tropical Breeze(Well-Worn)": "2.80",
  "FAMAS | Yeti Camo(Battle-Scarred)": "1.96",
  "Tec-9 | Remote Control(Battle-Scarred)": "1.55",
  "Five-SeveN | Silver Quartz(Well-Worn)": "0.50",
  "AUG | Condemned(Factory New)": "0.46",
  "AK-47 | Safari Mesh(Factory New)": "2.26",
  "AWP | Green Energy(Battle-Scarred)": "45.00",
  "SG 553 | Integrale(Field-Tested)": "9.37",
  "SSG 08 | Blush Pour(Well-Worn)": "2.69",
  "AUG | Random Access(Well-Worn)": "0.69",
  "M4A1-S | Control Panel(Minimal Wear)": "14.23",
  "Desert Eagle | Mint Fan(Well-Worn)": "2.34",
  "SG 553 | Integrale(Well-Worn)": "4.38",
  "Dual Berettas | Twin Turbo(Factory New)": "9.20",
  "P90 | Facility Negative(Battle-Scarred)": "0.14",
  "P250 | Red Tide(Well-Worn)": "2.89",
  "Sawed-Off | Snake Camo(Factory New)": "0.47",
  "M4A1-S | Glitched Paint(Battle-Scarred)": "16.98",
  "MAG-7 | Core Breach(Battle-Scarred)": "0.53",
  "SG 553 | Integrale(Factory New)": "80.13",
  "AK-47 | Midnight Laminate(Well-Worn)": "16.45",
  "Random Graffiti": "0.03",
  "Charm Detachment Pack": "0",
  "M4A1-S | Stratosphere(Battle-Scarred)": "30.98",
  "Desert Eagle | Mulberry(Well-Worn)": "18.89",
  "Tec-9 | Remote Control(Factory New)": "6.18",
  "AWP | Green Energy(Well-Worn)": "53.67",
  "AK-47 | Nouveau Rouge(Factory New)": "533.50",
  "M4A1-S | Stratosphere(Well-Worn)": "41.45",
  "M4A1-S | Stratosphere(Factory New)": "264.80",
  "USP-S | Bleeding Edge(Battle-Scarred)": "11.30",
  "MAG-7 | Core Breach(Factory New)": "5.71",
  "FAMAS | Yeti Camo(Well-Worn)": "2.54",
  "Dreams &amp; Nightmares Case": "2.23",
  "M4A1-S | Control Panel(Battle-Scarred)": "5.00",
  "USP-S | Forest Leaves(Factory New)": "0.92"
}
